oneagent/__init__.py
oneagent/common.py
oneagent/version.py
oneagent/_impl/__init__.py
oneagent/_impl/six.py
oneagent/_impl/util.py
oneagent/_impl/native/__init__.py
oneagent/_impl/native/libonesdk_shared.so
oneagent/_impl/native/nativeagent.py
oneagent/_impl/native/sdkctypesiface.py
oneagent/_impl/native/sdkdllinfo.py
oneagent/_impl/native/sdknulliface.py
oneagent/_impl/native/sdkversion.py
oneagent/sdk/__init__.py
oneagent/sdk/tracers.py
oneagent_sdk-1.5.2.20260107.153442.dist-info/licenses/LICENSE
oneagent_sdk-1.5.2.20260107.153442.dist-info/METADATA
oneagent_sdk-1.5.2.20260107.153442.dist-info/WHEEL
oneagent_sdk-1.5.2.20260107.153442.dist-info/top_level.txt
oneagent_sdk-1.5.2.20260107.153442.dist-info/zip-safe
oneagent_sdk-1.5.2.20260107.153442.dist-info/RECORD
