Metadata-Version: 2.4
Name: oneagent-sdk
Version: 1.5.2.20260107.153442
Summary: Dynatrace OneAgent SDK for Python
Home-page: https://github.com/Dynatrace/OneAgent-SDK-for-Python
Download-URL: https://pypi.org/project/oneagent-sdk/
Maintainer: Dynatrace LLC
Maintainer-email: dynatrace.oneagent.sdk@dynatrace.com
License: Apache License 2.0
Project-URL: Issue Tracker, https://github.com/Dynatrace/OneAgent-SDK-for-Python/issues
Project-URL: Documentation, https://dynatrace.github.io/OneAgent-SDK-for-Python/
Classifier: Development Status :: 5 - Production/Stable
Classifier: Intended Audience :: Developers
Classifier: License :: OSI Approved
Classifier: License :: OSI Approved :: Apache Software License
Classifier: Programming Language :: Python
Classifier: Programming Language :: Python :: 3
Classifier: Programming Language :: Python :: Implementation :: CPython
Classifier: Operating System :: POSIX :: Linux
Classifier: Operating System :: Microsoft :: Windows
Classifier: Topic :: System :: Monitoring
Requires-Python: >=2.7,!=3.0.*,!=3.1.*,!=3.2.*,!=3.3.*
License-File: LICENSE
Dynamic: classifier
Dynamic: description
Dynamic: description-content-type
Dynamic: download-url
Dynamic: home-page
Dynamic: license
Dynamic: license-file
Dynamic: maintainer
Dynamic: maintainer-email
Dynamic: project-url
Dynamic: requires-python
Dynamic: summary
